Metadata-Version: 2.1
Name: python-proxy-utils
Version: 0.1.0
Summary: Python Proxy Utils
Home-page: https://github.com/storerjeremy/python-proxy-utils
Author: Jeremy Storer
Author-email: storerjeremy@gmail.com
License: UNKNOWN
Platform: UNKNOWN
Classifier: Programming Language :: Python :: 3
Classifier: License :: OSI Approved :: MIT License
Classifier: Operating System :: OS Independent
